[
null,
{"id":1,"members":[{"enemyId":1,"x":165,"y":343,"hidden":false},{"enemyId":1,"x":321,"y":424,"hidden":false}],"name":"たまこうもり*2","pages":[{"conditions":{"actorHp":50,"actorId":1,"actorValid":false,"enemyHp":50,"enemyIndex":0,"enemyValid":false,"switchId":1,"switchValid":false,"turnA":0,"turnB":0,"turnEnding":false,"turnValid":true},"list":[{"code":231,"indent":0,"parameters":[1,"00立ち絵a",1,0,691,492,100,100,255,0]},{"code":0,"indent":0,"parameters":[]}],"span":0}]},
{"id":2,"members":[{"enemyId":2,"x":154,"y":364,"hidden":false},{"enemyId":2,"x":368,"y":331,"hidden":false}],"name":"うさみみピクシー*2","pages":[{"conditions":{"actorHp":50,"actorId":1,"actorValid":false,"enemyHp":50,"enemyIndex":0,"enemyValid":false,"switchId":1,"switchValid":false,"turnA":0,"turnB":0,"turnEnding":false,"turnValid":true},"list":[{"code":231,"indent":0,"parameters":[1,"00立ち絵a",1,0,691,492,100,100,255,0]},{"code":0,"indent":0,"parameters":[]}],"span":0}]},
{"id":3,"members":[{"enemyId":3,"x":150,"y":376,"hidden":false},{"enemyId":3,"x":324,"y":444,"hidden":false}],"name":"セメントスライム*2","pages":[{"conditions":{"actorHp":50,"actorId":1,"actorValid":false,"enemyHp":50,"enemyIndex":0,"enemyValid":false,"switchId":1,"switchValid":false,"turnA":0,"turnB":0,"turnEnding":false,"turnValid":true},"list":[{"code":231,"indent":0,"parameters":[1,"00立ち絵a",1,0,691,492,100,100,255,0]},{"code":0,"indent":0,"parameters":[]}],"span":0}]},
{"id":4,"members":[{"enemyId":4,"x":139,"y":349,"hidden":false},{"enemyId":4,"x":287,"y":444,"hidden":false}],"name":"テンタジェル*2","pages":[{"conditions":{"actorHp":50,"actorId":1,"actorValid":false,"enemyHp":50,"enemyIndex":0,"enemyValid":false,"switchId":1,"switchValid":false,"turnA":0,"turnB":0,"turnEnding":false,"turnValid":true},"list":[{"code":231,"indent":0,"parameters":[1,"00立ち絵a",1,0,691,492,100,100,255,0]},{"code":0,"indent":0,"parameters":[]}],"span":0}]},
{"id":5,"members":[{"enemyId":5,"x":234,"y":421,"hidden":false}],"name":"岩石魔人","pages":[{"conditions":{"actorHp":50,"actorId":1,"actorValid":false,"enemyHp":50,"enemyIndex":0,"enemyValid":false,"switchId":1,"switchValid":false,"turnA":0,"turnB":0,"turnEnding":false,"turnValid":true},"list":[{"code":231,"indent":0,"parameters":[1,"00立ち絵a",1,0,691,492,100,100,255,0]},{"code":121,"indent":0,"parameters":[4,4,0]},{"code":0,"indent":0,"parameters":[]}],"span":0}]},
{"id":6,"members":[{"enemyId":6,"x":240,"y":426,"hidden":false}],"name":"ヌマヌシ","pages":[{"conditions":{"actorHp":50,"actorId":1,"actorValid":false,"enemyHp":50,"enemyIndex":0,"enemyValid":false,"switchId":1,"switchValid":false,"turnA":0,"turnB":0,"turnEnding":false,"turnValid":true},"list":[{"code":231,"indent":0,"parameters":[1,"00立ち絵a",1,0,691,492,100,100,255,0]},{"code":0,"indent":0,"parameters":[]}],"span":0}]},
{"id":7,"members":[{"enemyId":7,"x":198,"y":379,"hidden":false}],"name":"チュートリアル","pages":[{"conditions":{"actorHp":50,"actorId":1,"actorValid":false,"enemyHp":50,"enemyIndex":0,"enemyValid":false,"switchId":1,"switchValid":false,"turnA":0,"turnB":0,"turnEnding":false,"turnValid":true},"list":[{"code":231,"indent":0,"parameters":[1,"00立ち絵a",1,0,691,492,100,100,255,0]},{"code":312,"indent":0,"parameters":[0,1,1,0,200]},{"code":333,"indent":0,"parameters":[-1,0,3]},{"code":313,"indent":0,"parameters":[0,0,1,29]},{"code":101,"indent":0,"parameters":["リア01",0,0,2]},{"code":401,"indent":0,"parameters":["リア"]},{"code":401,"indent":0,"parameters":["「こんなやつあたしのスキルでサクッと……」"]},{"code":101,"indent":0,"parameters":["リア01",4,0,2]},{"code":401,"indent":0,"parameters":["リア"]},{"code":401,"indent":0,"parameters":["「ってあれ！！？　ＭＰがないっ！？"]},{"code":401,"indent":0,"parameters":["　なんでだよ……！」"]},{"code":101,"indent":0,"parameters":["ドロシー01",0,0,2]},{"code":401,"indent":0,"parameters":["ドロシー"]},{"code":401,"indent":0,"parameters":["「ここは落っこちてきたニンゲンを"]},{"code":401,"indent":0,"parameters":["　閉じ込めておく場所だからね～」"]},{"code":101,"indent":0,"parameters":["ドロシー01",0,0,2]},{"code":401,"indent":0,"parameters":["ドロシー"]},{"code":401,"indent":0,"parameters":["「そう簡単に逃げられないように"]},{"code":401,"indent":0,"parameters":["　地下ではニンゲン由来の魔力は"]},{"code":401,"indent":0,"parameters":["　全部吸い取られちゃうんだよ」"]},{"code":101,"indent":0,"parameters":["リア01",4,0,2]},{"code":401,"indent":0,"parameters":["リア"]},{"code":401,"indent":0,"parameters":["「そ、そんなの聞いてないぞ！"]},{"code":401,"indent":0,"parameters":["　ってしまった……！！」"]},{"code":117,"indent":0,"parameters":[99]},{"code":101,"indent":0,"parameters":["リア01",6,0,2]},{"code":401,"indent":0,"parameters":["リア"]},{"code":401,"indent":0,"parameters":["「はっ、はっ、ははは……"]},{"code":401,"indent":0,"parameters":["　このっ！！」"]},{"code":339,"indent":0,"parameters":[1,1,1,-1]},{"code":101,"indent":0,"parameters":["リア01",4,0,2]},{"code":401,"indent":0,"parameters":["リア"]},{"code":401,"indent":0,"parameters":["「くそっ、やっぱりスキルじゃないと……！」"]},{"code":117,"indent":0,"parameters":[100]},{"code":101,"indent":0,"parameters":["リア01",6,0,2]},{"code":401,"indent":0,"parameters":["リア"]},{"code":401,"indent":0,"parameters":["「た、たすけてぇ……っ！」"]},{"code":101,"indent":0,"parameters":["ドロシー01",1,0,2]},{"code":401,"indent":0,"parameters":["ドロシー"]},{"code":401,"indent":0,"parameters":["「だから言ったのに～"]},{"code":401,"indent":0,"parameters":["　私のＭＰ分けてあげるよ！」"]},{"code":250,"indent":0,"parameters":[{"name":"Heal1","volume":90,"pitch":100,"pan":0}]},{"code":312,"indent":0,"parameters":[0,1,0,0,100]},{"code":101,"indent":0,"parameters":["",0,0,2]},{"code":401,"indent":0,"parameters":["リアのＭＰが１００回復した！"]},{"code":101,"indent":0,"parameters":["リア01",2,0,2]},{"code":401,"indent":0,"parameters":["リア"]},{"code":401,"indent":0,"parameters":["「ＭＰが……！"]},{"code":401,"indent":0,"parameters":["　これなら……っ！！」"]},{"code":333,"indent":0,"parameters":[-1,1,3]},{"code":339,"indent":0,"parameters":[1,1,12,-1]},{"code":333,"indent":0,"parameters":[-1,0,1]},{"code":0,"indent":0,"parameters":[]}],"span":0}]},
{"id":8,"members":[{"enemyId":7,"x":159,"y":316,"hidden":false},{"enemyId":7,"x":324,"y":394,"hidden":false}],"name":"テスト","pages":[{"conditions":{"actorHp":50,"actorId":1,"actorValid":false,"enemyHp":50,"enemyIndex":0,"enemyValid":false,"switchId":1,"switchValid":false,"turnA":0,"turnB":0,"turnEnding":false,"turnValid":true},"list":[{"code":231,"indent":0,"parameters":[1,"00立ち絵a",1,0,691,492,100,100,255,0]},{"code":0,"indent":0,"parameters":[]}],"span":0}]},
{"id":9,"members":[{"enemyId":1,"x":213,"y":382,"hidden":false}],"name":"たまこうもり","pages":[{"conditions":{"actorHp":50,"actorId":1,"actorValid":false,"enemyHp":50,"enemyIndex":0,"enemyValid":false,"switchId":1,"switchValid":false,"turnA":0,"turnB":0,"turnEnding":false,"turnValid":true},"list":[{"code":231,"indent":0,"parameters":[1,"00立ち絵a",1,0,691,492,100,100,255,0]},{"code":0,"indent":0,"parameters":[]}],"span":0}]},
{"id":10,"members":[{"enemyId":2,"x":213,"y":379,"hidden":false}],"name":"うさみみピクシー","pages":[{"conditions":{"actorHp":50,"actorId":1,"actorValid":false,"enemyHp":50,"enemyIndex":0,"enemyValid":false,"switchId":1,"switchValid":false,"turnA":0,"turnB":0,"turnEnding":false,"turnValid":true},"list":[{"code":231,"indent":0,"parameters":[1,"00立ち絵a",1,0,691,492,100,100,255,0]},{"code":0,"indent":0,"parameters":[]}],"span":0}]},
{"id":11,"members":[{"enemyId":2,"x":264,"y":337,"hidden":false},{"enemyId":1,"x":126,"y":444,"hidden":false},{"enemyId":1,"x":396,"y":436,"hidden":false}],"name":"うさみみピクシー, たまこうもり*2","pages":[{"conditions":{"actorHp":50,"actorId":1,"actorValid":false,"enemyHp":50,"enemyIndex":0,"enemyValid":false,"switchId":1,"switchValid":false,"turnA":0,"turnB":0,"turnEnding":false,"turnValid":true},"list":[{"code":231,"indent":0,"parameters":[1,"00立ち絵a",1,0,691,492,100,100,255,0]},{"code":0,"indent":0,"parameters":[]}],"span":0}]},
{"id":12,"members":[],"name":"","pages":[{"conditions":{"actorHp":50,"actorId":1,"actorValid":false,"enemyHp":50,"enemyIndex":0,"enemyValid":false,"switchId":1,"switchValid":false,"turnA":0,"turnB":0,"turnEnding":false,"turnValid":false},"list":[{"code":0,"indent":0,"parameters":[]}],"span":0}]},
{"id":13,"members":[],"name":"","pages":[{"conditions":{"actorHp":50,"actorId":1,"actorValid":false,"enemyHp":50,"enemyIndex":0,"enemyValid":false,"switchId":1,"switchValid":false,"turnA":0,"turnB":0,"turnEnding":false,"turnValid":false},"list":[{"code":0,"indent":0,"parameters":[]}],"span":0}]},
{"id":14,"members":[],"name":"","pages":[{"conditions":{"actorHp":50,"actorId":1,"actorValid":false,"enemyHp":50,"enemyIndex":0,"enemyValid":false,"switchId":1,"switchValid":false,"turnA":0,"turnB":0,"turnEnding":false,"turnValid":false},"list":[{"code":0,"indent":0,"parameters":[]}],"span":0}]},
{"id":15,"members":[],"name":"","pages":[{"conditions":{"actorHp":50,"actorId":1,"actorValid":false,"enemyHp":50,"enemyIndex":0,"enemyValid":false,"switchId":1,"switchValid":false,"turnA":0,"turnB":0,"turnEnding":false,"turnValid":false},"list":[{"code":0,"indent":0,"parameters":[]}],"span":0}]}
]